oauth2_facebook_login/__init__.py
oauth2_facebook_login/functions.py
oauth2_facebook_login-1.0.0.dist-info/DESCRIPTION.rst
oauth2_facebook_login-1.0.0.dist-info/METADATA
oauth2_facebook_login-1.0.0.dist-info/RECORD
oauth2_facebook_login-1.0.0.dist-info/WHEEL
oauth2_facebook_login-1.0.0.dist-info/metadata.json
oauth2_facebook_login-1.0.0.dist-info/top_level.txt
