Metadata-Version: 2.0
Name: oauth2-facebook-login
Version: 1.0.0
Summary: Returns Facebook OAuth2 access token
Home-page: https://github.com/joeyism/oauth2_facebook_login
Author: Joey Sham
Author-email: sham.joey@gmail.com
License: UNKNOWN
Download-URL: https://github.com/joeyism/oauth2_facebook_login/dist/1.0.0.tar.gz
Keywords: oauth2,facebook,login
Platform: UNKNOWN
Requires-Dist: selenium
Requires-Dist: requests-oauthlib
